{
    " child_seat available": {
        "result": "Unknown",
        "evidence": null,
        "confidence": 0.4
    },
    "Spacious seating": {
        "result": "Yes",
        "evidence": "店面不大但位置寬敞舒適",
        "confidence": 0.9
    },
    "Kids menu available": {
        "result": "Unknown",
        "evidence": null,
        "confidence": 0.4
    },
    "kid_noise_tolerant": {
        "result": "Yes",
        "evidence": "感覺比較適合聚餐",
        "confidence": 0.9
    },
    "parent_friendly_score": 2,
    "parent_friendly_level": "中",
    "reason": "綜合評估",
    "generated_signals": [
        "店面不大但位置寬敞舒適",
        "感覺比較適合聚餐"
    ],
    "generated_summary": "評論指出這家餐廳空間寬敞、對親子家庭友善。"
}